docbuilderpy/__init__.py
docbuilderpy/analyze_definitions.py
docbuilderpy/cli.py
docbuilderpy/definitions.py
docbuilderpy/load_file.py
docbuilderpy/file_generators/__init__.py
docbuilderpy/file_generators/markdown.py
docbuilderpy/generators/__init__.py
docbuilderpy/generators/generator.py
docbuilderpy/generators/multi_file_generator.py
docbuilderpy/generators/single_file_generator.py
tests/__init__.py
tests/test_analyze_definitions.py
tests/test_definitions.py
tests/test_load_file.py
tests/utility.py
tests/file_generators/__init__.py
tests/file_generators/test_markdown.py
tests/generators/__init__.py
tests/generators/test_generator.py
tests/generators/test_multi_file_generator.py
tests/generators/test_single_file_generator.py
docbuilderpy-0.0.4.dist-info/LICENSE
docbuilderpy-0.0.4.dist-info/METADATA
docbuilderpy-0.0.4.dist-info/WHEEL
docbuilderpy-0.0.4.dist-info/entry_points.txt
docbuilderpy-0.0.4.dist-info/top_level.txt
docbuilderpy-0.0.4.dist-info/RECORD
