Metadata-Version: 2.1
Name: docbuilderpy
Version: 0.0.4
Summary: Simple creation of documentation for Python projects.
Author: Jan-Markus Langer
License-File: LICENSE
Requires-Dist: click
